secrettoenv/__init__.py
secrettoenv/cli.py
secrettoenv/my-secret.json
secrettoenv/my-secret.yaml
secrettoenv/secret_from_file.py
secrettoenv/secret_from_kubernetes.py
secrettoenv-0.1.0.dist-info/LICENSE
secrettoenv-0.1.0.dist-info/METADATA
secrettoenv-0.1.0.dist-info/WHEEL
secrettoenv-0.1.0.dist-info/entry_points.txt
secrettoenv-0.1.0.dist-info/RECORD
