Metadata-Version: 2.1
Name: secrettoenv
Version: 0.1.0
Summary: Python package to convert Kubernetes secrets into .env files with key-value pairs for easier local development.
License: MIT
Author: nithin-nk
Author-email: nithin08anil@gmail.com
Requires-Python: >=3.9,<4.0
Classifier: License :: OSI Approved :: MIT License
Classifier: Programming Language :: Python :: 3
Classifier: Programming Language :: Python :: 3.9
Classifier: Programming Language :: Python :: 3.10
Classifier: Programming Language :: Python :: 3.11
Classifier: Programming Language :: Python :: 3.12
Classifier: Programming Language :: Python :: 3.13
Requires-Dist: click (>=8.1.7,<9.0.0)
Requires-Dist: kubernetes (>=31.0.0,<32.0.0)
